fewspy/__init__.py
fewspy/api.py
fewspy/time_series.py
fewspy/cache/__init__.py
fewspy/cache/manifest.py
fewspy/cache/time_series_cache.py
fewspy/io/__init__.py
fewspy/io/header_file.py
fewspy/io/read_json.py
fewspy/io/read_netcdf.py
fewspy/io/read_parquet.py
fewspy/io/read_xml.py
fewspy/io/write_netcdf.py
fewspy/utils/conversions.py
fewspy/utils/timer.py
fewspy/utils/transformations.py
fewspy/utils/url.py
fewspy/wrappers/__init__.py
fewspy/wrappers/get_filters.py
fewspy/wrappers/get_locations.py
fewspy/wrappers/get_parameters.py
fewspy/wrappers/get_qualifiers.py
fewspy/wrappers/get_time_series.py
fewspy/wrappers/get_time_series_async.py
fewspy/wrappers/get_timezone_id.py
fewspy-2025.11.0.dist-info/METADATA
fewspy-2025.11.0.dist-info/WHEEL
fewspy-2025.11.0.dist-info/licenses/LICENSE
fewspy-2025.11.0.dist-info/RECORD
