Metadata-Version: 2.4
Name: fewspy
Version: 2025.11.0
Summary: A Python API for the Deltares FEWS PI REST Web Service
Project-URL: Source, https://github.com/d2hydro/fewspy
Author-email: Daniel Tollenaar <daniel@d2hydro.nl>
License: MIT
License-File: LICENSE
Requires-Python: <3.14,>=3.9
Requires-Dist: aiohttp
Requires-Dist: geopandas
Requires-Dist: lxml
Requires-Dist: nest-asyncio
Requires-Dist: netcdf4
Requires-Dist: pandas
Requires-Dist: pyarrow
Requires-Dist: pydantic
Requires-Dist: requests
Requires-Dist: xarray
Provides-Extra: tests
Requires-Dist: pytest; extra == 'tests'
